pyet/__init__.py
pyet/combination.py
pyet/meteo_utils.py
pyet/rad_utils.py
pyet/radiation.py
pyet/temperature.py
pyet/utils.py
pyet/version.py
pyet-1.4.0.dist-info/licenses/LICENSE
pyet-1.4.0.dist-info/METADATA
pyet-1.4.0.dist-info/WHEEL
pyet-1.4.0.dist-info/top_level.txt
pyet-1.4.0.dist-info/RECORD
