Metadata-Version: 2.4
Name: pyet
Version: 1.4.0
Summary: pyet - Estimation of Potential Evaporation
Author-email: Matevz Vremec <matevz.vremec@uni-graz.at>, Raoul Collenteur <raoulcollenteur@gmail.com>
License: MIT License
Project-URL: Source, https://github.com/phydrus/pyet
Project-URL: Tracker, https://github.com/phydrus/pyet/issues
Project-URL: Help, https://github.com/phydrus/pyet/discussions
Project-URL: homepage, https://github.com/phydrus/pyet
Project-URL: repository, https://github.com/phydrus/pyet
Project-URL: documentation, https://github.com/phydrus/pyet/discussions
Classifier: Development Status :: 5 - Production/Stable
Classifier: Intended Audience :: Science/Research
Classifier: Intended Audience :: Other Audience
Classifier: License :: OSI Approved :: MIT License
Classifier: Programming Language :: Python :: 3 :: Only
Classifier: Programming Language :: Python :: 3.10
Classifier: Programming Language :: Python :: 3.11
Classifier: Programming Language :: Python :: 3.12
Classifier: Programming Language :: Python :: 3.13
Classifier: Topic :: Scientific/Engineering :: Hydrology
Requires-Python: >=3.10
License-File: LICENSE
Requires-Dist: numpy>=1.16
Requires-Dist: xarray>=0.18.0
Requires-Dist: pandas>=2.1
Provides-Extra: rtd
Requires-Dist: sphinx-autodoc-typehints; extra == "rtd"
Requires-Dist: Ipython; extra == "rtd"
Requires-Dist: ipykernel; extra == "rtd"
Requires-Dist: pydata-sphinx-theme; extra == "rtd"
Requires-Dist: sphinx-gallery; extra == "rtd"
Requires-Dist: sphinx>=3.1; extra == "rtd"
Requires-Dist: sphinxcontrib-bibtex; extra == "rtd"
Requires-Dist: matplotlib; extra == "rtd"
Requires-Dist: myst-nb; extra == "rtd"
Requires-Dist: numpydoc; extra == "rtd"
Requires-Dist: sphinx-design; extra == "rtd"
Requires-Dist: seaborn; extra == "rtd"
Requires-Dist: netcdf4; extra == "rtd"
Requires-Dist: scikit-learn; extra == "rtd"
Requires-Dist: scipy; extra == "rtd"
Requires-Dist: spotpy; extra == "rtd"
Requires-Dist: openpyxl; extra == "rtd"
Dynamic: license-file
